yagwr/__init__.py
yagwr/async_in_thread.py
yagwr/checker.py
yagwr/logger.py
yagwr/rules.py
yagwr/webhooks.py
yagwr/bin/__init__.py
yagwr/bin/yagwr.py
yagwr-0.1.3.dist-info/licenses/LICENSE.txt
yagwr-0.1.3.dist-info/METADATA
yagwr-0.1.3.dist-info/WHEEL
yagwr-0.1.3.dist-info/entry_points.txt
yagwr-0.1.3.dist-info/top_level.txt
yagwr-0.1.3.dist-info/RECORD
