Metadata-Version: 2.4
Name: yagwr
Version: 0.1.3
Summary: Yet Another Gitlab Webhook Runner
Home-page: https://github.com/shaoran/yagwr
Author: Pablo Yanez
License: GPL-2.0-only
Project-URL: Documentation, https://github.com/shaoran/yagwr
Project-URL: Source, https://github.com/shaoran/yagwr
Platform: any
Classifier: Development Status :: 5 - Production/Stable
Classifier: Programming Language :: Python
Classifier: License :: OSI Approved :: GNU General Public License v2 (GPLv2)
Classifier: Operating System :: OS Independent
Classifier: Programming Language :: Python :: 3.7
Classifier: Programming Language :: Python :: 3.8
Classifier: Programming Language :: Python :: 3.9
Classifier: Topic :: Software Development
Classifier: Topic :: Software Development :: Version Control
Classifier: Topic :: Software Development :: Version Control :: Git
Requires-Python: >=3.7
License-File: LICENSE.txt
Requires-Dist: PyYAML
Requires-Dist: importlib-metadata; python_version < "3.8"
Provides-Extra: testing
Requires-Dist: setuptools; extra == "testing"
Requires-Dist: pytest; extra == "testing"
Requires-Dist: pytest-cov; extra == "testing"
Dynamic: license-file
